mcp_rag/__init__.py
mcp_rag/cli.py
mcp_rag/config.py
mcp_rag/database.py
mcp_rag/document_processor.py
mcp_rag/embedding.py
mcp_rag/http_server.py
mcp_rag/llm.py
mcp_rag/main.py
mcp_rag/mcp_server.py
mcp_rag/text_splitter.py
mcp_rag-0.5.6.dist-info/METADATA
mcp_rag-0.5.6.dist-info/WHEEL
mcp_rag-0.5.6.dist-info/entry_points.txt
mcp_rag-0.5.6.dist-info/top_level.txt
mcp_rag-0.5.6.dist-info/RECORD
