Metadata-Version: 2.4
Name: mcp-rag
Version: 0.5.6
Summary: 基于mcp的rag服务
Requires-Python: >=3.13
Requires-Dist: fastapi>=0.104.0
Requires-Dist: uvicorn[standard]>=0.24.0
Requires-Dist: pydantic>=2.5.0
Requires-Dist: pydantic-settings>=2.1.0
Requires-Dist: chromadb>=0.4.18
Requires-Dist: numpy>=1.24.0
Requires-Dist: scikit-learn>=1.3.0
Requires-Dist: httpx>=0.25.0
Requires-Dist: python-multipart>=0.0.6
Requires-Dist: mcp>=0.1.0
Requires-Dist: typer>=0.9.0
Requires-Dist: PyPDF2>=3.0.0
Requires-Dist: python-docx>=1.1.0
Provides-Extra: local-embeddings
Requires-Dist: sentence-transformers>=2.2.2; extra == "local-embeddings"
